Workbook

Sheet 🏠 Dashboard
A1: WIKIMEDIA COMMUNITY KILIMANJARO
A2: Activity Expense Dashboard — August 2025 to May 2026
B4: TOTAL ACTIVITIES | D4: COMPLETED | F4: PLANNED | H4: TOTAL SPENT (USD)
B5: 16 | D5: =COUNTIF('📋 Activity Index'!E5:E21,"Completed") -> 11 | F5: =COUNTIF('📋 Activity Index'!E11:E35,"Planned") -> 5 | H5: =G37+'💰 Salary & Stipend'!R14 -> 18516.289
A8: 📂 QUICK ACCESS — CLICK ANY EVENT TO OPEN ITS EXPENSE SHEET
B9: # | C9: Activity | D9: Date | E9: Status | F9: Total (TZS) | G9: Total (USD) | H9: Open ↗
A10: Wiki Monthly Series
B11: 1 | C11: Monthly In-Person Edit-a-thon — August 2025 | D11: August 2025 | E11: Completed | H11: 📂 Open
B12: 2 | C12: Monthly In-Person Edit-a-thon — March 2026 | D12: March 2026 | E12: Planned | F12: ='📋 Activity Index'!G13 | G12: ='Mar26 Monthly Edit-a-thon'!K23 -> 0 | H12: 📂 Open
B13: 3 | C13: Monthly In-Person Edit-a-thon — April 2026 | D13: April 2026 | E13: Planned | F13: ='📋 Activity Index'!G14 | G13: ='Apr26 Monthly Edit-a-thon'!I22 -> 0 | H13: 📂 Open
B14: 4 | C14: Monthly In-Personal Edit-a-thon - July | D14: 45839 | E14: Completed | G14: ='Monthly In-Personal Edit-a-thon'!K23 -> 1173.84
B15: 5 | C15: Monthly In-Person Edit-a-thon — October 2025 | D15: October 2025 | E15: Completed | F15: ='📋 Activity Index'!G6 | G15: ='📋 Activity Index'!H6 -> 1149.312 | H15: 📂 Open
B16: 6 | C16: Monthly In-Person Edit-a-thon — December 2025 | D16: 20.12.2025 | E16: Completed | F16: ='📋 Activity Index'!G7 | G16: ='📋 Activity Index'!H7 -> 1121.28 | H16: 📂 Open
A17: Wikimalkia
B18: 7 | C18: Wikimalkia Training — October 2025 | D18: October 2025 | E18: Completed | F18: ='📋 Activity Index'!G8 | G18: ='📋 Activity Index'!H8 -> 1177.05 | H18: 📂 Open
B19: 8 | C19: Wikimalkia Workshop — February 2026 | D19: February 2026 | E19: Completed | F19: ='📋 Activity Index'!G15 | G19: ='Feb26 Wikimalkia Workshop'!K23 -> 1213.26 | H19: 📂 Open
B20: 9 | C20: Wikimalkia Edit-a-thon — December 2025 | D20: December 2025 | E20: Completed | F20: ='📋 Activity Index'!G9 | G20: ='📋 Activity Index'!H9 -> 1092.81 | H20: 📂 Open
A21: Error, Fix and Contribute
B22: 10 | C22: Error, Fix and Contribute Workshop — November 2025 | D22: November 2025 | E22: Completed | F22: ='📋 Activity Index'!G10 | G22: ='📋 Activity Index'!H10 -> 1116.9 | H22: 📂 Open
B23: 11 | C23: Error, Fix and Contribute Training — January 2026 | D23: January 2026 | E23: Completed | F23: ='📋 Activity Index'!G11 | G23: ='📋 Activity Index'!H11 -> 1254.87 | H23: 📂 Open
A24: Let's Connect
B25: 12 | C25: Let's Connect: Inclusive Collaboration Space — Event 2 of 2 | D25: [Date TBD] | E25: Planned | F25: ='📋 Activity Index'!G19 | G25: ='📋 Activity Index'!H19 -> 0 | H25: 📂 Open
B26: 13 | C26: Let's Connect: Inclusive Collaboration Space — Event 1 of 2 | D26: [Date of Event 1] | E26: Completed | F26: ='📋 Activity Index'!G12 | G26: ='Lets Connect Event 1'!I22 -> 1414.74 | H26: 📂 Open
A27: Feminism and Folklore
B28: 14 | C28: Feminism and Folklore Edit-a-thon — February 2026 | D28: February 2026 | E28: Planned | F28: ='📋 Activity Index'!G16 | G28: ='Feb26 Feminism Folklore'!I22 -> 0 | H28: 📂 Open
A29: Wikimedia Community Kilimanjaro
B30: 15 | C30: Wikimedia Community Kilimanjaro Training — March 2026 | D30: March 2026 | E30: Planned | F30: ='📋 Activity Index'!G17 | G30: ='📋 Activity Index'!H17 -> 0 | H30: 📂 Open
B31: 16 | H31: 📂 Open
B33: 15 | C33: Kiwix Program for Schools | D33: August-November | E33: Completed | G33: ='Kiwix for shool-program'!I22 -> 951.74 | H33: 📂 Open
A34: Wikimedia Community Kilimanjaro
B35: 16 | C35: Wikimedia Community Kilimanjaro Wrap-up — May 2026 | D35: May 2026 | E35: Planned | F35: ='📋 Activity Index'!G20 | G35: ='Aug25 Monthly Edit-a-thon'!K23 -> 1149.312 | H35: 📂 Open
A37: GRAND TOTAL — ALL ACTIVITIES + SALARY + ADMIN | F37: ='📋 Activity Index'!G21 | G37: ='📋 Activity Index'!H22 -> 12916.292
A39: 📊 OTHER SHEETS — QUICK ACCESS
A40: 📋 | C40: All activities consolidated budget tracker | G40: 📂 Open
A41: 💰 | C41: Staff salaries, stipends, honoraria & facilitator fees | G41: 📂 Open
A42: 🗂️ | C42: Social media, communication, printing & bank charges | G42: 📂 Open
A44: ★ Click any activity name or 📂 Open button to navigate directly to its expense sheet. All totals update automatically as you fill in data.

Sheet 📋 Activity Index
A1: ◀ BACK TO DASHBOARD
A2: WIKIMEDIA COMMUNITY KILIMANJARO EXPENSE REPORTS INDEX
A3: Click any activity row to navigate to its expense sheet. Fill in blue cells with actual figures.
A4: # | B4: Activity | C4: Program | D4: Date | E4: Status | F4: Sheet Name | G4: Total (TZS) | H4: Total (USD)
B5: Monthly In-Person Edit-a-thon July 2025 | C5: Wiki Monthly Edit-a-thon | D5: 45839 | E5: Completed | F5: Monthly In-Personal Edit-a-thon - July | H5: ='Monthly In-Personal Edit-a-thon'!K23 -> 1173.84
A6: 1 | B6: Monthly In-Person Edit-a-thon — August 2025 | C6: Wiki Monthly Edit-a-thon | D6: August 2025 | E6: Completed | F6: Aug25 Monthly Edit-a-thon | H6: ='Aug25 Monthly Edit-a-thon'!K23 -> 1149.312
A7: 2 | B7: Monthly In-Person Edit-a-thon — October 2025 | C7: Wiki Monthly Edit-a-thon | D7: October 2025 | E7: Completed | F7: Oct25 Monthly Edit-a-thon | H7: ='Oct25 Monthly Edit-a-thon'!K23 -> 1121.28
A8: 3 | B8: Monthly In-Person Edit-a-thon — December 2025 | C8: Wiki Monthly Edit-a-thon | D8: 20.12.2024 | E8: Completed | F8: Dec25 Monthly Edit-a-thon | H8: ='Dec25 Monthly Edit-a-thon'!K23 -> 1177.05
A9: 4 | B9: Wikimalkia Training — October 2025 | C9: Wikimalkia | D9: October 2025 | E9: Completed | F9: Oct25 Wikimalkia Training | H9: ='Oct25 Wikimalkia Training'!K23 -> 1092.81
A10: 5 | B10: Wikimalkia Edit-a-thon — December 2025 | C10: Wikimalkia | D10: December 2025 | E10: Completed | F10: Dec25 Wikimalkia Edit-a-thon | H10: ='Dec25 Wikimalkia Edit-a-thon'!K23 -> 1116.9
A11: 6 | B11: Error, Fix and Contribute Workshop — November 2025 | C11: Error, Fix and Contribute | D11: November 2025 | E11: Completed | F11: Nov25 Error Fix Workshop | H11: ='Nov25 Error Fix Workshop'!K23 -> 1254.87
A12: 7 | B12: Error, Fix and Contribute Training — January 2026 | C12: Error, Fix and Contribute | D12: January 2026 | E12: Completed | F12: Jan26 Error Fix Training | H12: ='Jan26 Error Fix Training'!K23 -> 1250.49
A13: 8 | B13: Let's Connect: Inclusive Collaboration Space — Event 1 of 2 | C13: Let's Connect — Inclusive Collaboration Space | D13: [Date of Event 1] | E13: Completed | F13: Lets Connect Event 1 | H13: ='Lets Connect Event 1'!I22 -> 1414.74
A14: 9 | B14: Monthly In-Person Edit-a-thon — March 2026 | C14: Wiki Monthly Edit-a-thon | D14: March 2026 | E14: Planned | F14: Mar26 Monthly Edit-a-thon | H14: ='Mar26 Monthly Edit-a-thon'!K23 -> 0
A15: 10 | B15: Monthly In-Person Edit-a-thon — April 2026 | C15: Wiki Monthly Edit-a-thon | D15: April 2026 | E15: Planned | F15: Apr26 Monthly Edit-a-thon | H15: ='Apr26 Monthly Edit-a-thon'!I22 -> 0
A16: 11 | B16: Wikimalkia Workshop — February 2026 | C16: Wikimalkia | D16: February 2026 | E16: Completed | F16: Feb26 Wikimalkia Workshop | H16: ='Feb26 Wikimalkia Workshop'!K23 -> 1213.26
A17: 12 | B17: Feminism and Folklore Edit-a-thon — February 2026 | C17: Feminism and Folklore | D17: February 2026 | E17: Planned | F17: Feb26 Feminism Folklore | H17: ='Feb26 Feminism Folklore'!I22 -> 0
B18: Kiwix Program for Schools | C18: Kiwix Program for Schools | D18: September - November | E18: Completed | F18: Kiwix for school-program | H18: ='Kiwix for shool-program'!I22 -> 951.74
A19: 13 | B19: Wikimedia Community Kilimanjaro Training — March 2026 | C19: Wikimedia Community Kilimanjaro | D19: March 2026 | E19: Planned | F19: Mar26 WCK Training | H19: ='Mar26 WCK Training'!I22 -> 0
A20: 14 | B20: Let's Connect: Inclusive Collaboration Space — Event 2 of 2 | C20: Let's Connect — Inclusive Collaboration Space | D20: [Date TBD] | E20: Planned | F20: Lets Connect Event 2 | H20: ='Lets Connect Event 2'!I22 -> 0
H21: ='Aug25 Monthly Edit-a-thon'!K37
A22: GRAND TOTAL — ALL ACTIVITIES | H22: =Sum(H5:H20) -> 12916.292
A23: ★ TZS column = enter actual spend in Tanzanian Shillings. USD pulls automatically from each sheet. Grand total includes activity expenses + salary/stipend + admin costs.
A25: TOTAL BY PROGRAM
A26: Program | G26: Total TZS | H26: Total USD
A27: Wiki Monthly Series | G27: =G8+G9+G15 -> 0 | H27: =H7+H8+H14 -> 2298.33
A28: Wikimalkia | G28: =G9+G10+G16 -> 0 | H28: =H8+H9+H15 -> 2269.86
A29: Error, Fix and Contribute | G29: =G10+G11+G17 -> 0 | H29: =H9+H10+H16 -> 3422.97
A30: Feminism and Folklore | G30: =G11+G12+G18 -> 0 | H30: =H10+H11+H17 -> 2371.77
A31: Wikimedia Community Kilimanjaro | G31: =G12+G13+G19 -> 0 | H31: =H11+H12+H18 -> 3457.1
A32: Let's Connect | G32: =G13+G14+G20 -> 0 | H32: =H12+H13+H19 -> 2665.23
A33: Salary & Stipend | G33: ='💰 Salary & Stipend'!P14 -> 13533100 | H33: ='💰 Salary & Stipend'!R14 -> 5599.9968
A34: Administrative Costs | G34: ='🗂️ Administrative Costs'!E41 -> 0 | H34: ='🗂️ Administrative Costs'!I41 -> 0

Sheet Monthly In-Personal Edit-a-thon
A1: WIKIMEDIA COMMUNITY KILIMANJARO —ACTIVITY EXPENSE REPORT
A2: ◀ BACK TO DASHBOARD | E2: ◀ BACK TO INDEX
A3: Project | E3: Wiki Monthly Edit-a-thon
A4: Activity | E4: Monthly In-Person Edit-a-thon — August 2025
A5: Date of event | E5: August 2025 | I5: Status | K5: Completed
A6: Venue
A7: No. of Participants | E7: Prepared by
A9: Payment details
A10: Conversion rate (xe.com) | E10: 0.000438
A12: Expense details
A13: Date of conversion: | E13: [Enter date currency was converted]
A14: Description | C14: Comments | D14: Cost of Unity in Local currency | E14: Cost (in local currency) | F14: Expense type | G14: Receipt? | H14: Number of Unit | I14: Local currency (please select) | J14: Conversion rate (if known) | K14: Receipt converted to USD
A15: Venue / Room Hire | C15: Venue hire for the event | D15: 8000 | E15: =H15*D15 -> 240000 | F15: Venue | H15: 30 | I15: TZS - Tanzanian Shilling | J15: =$E10 -> 0.000438 | K15: =IF(E15="",0,E15*$E10) -> 105.12
A16: Food and drinks | C16: Refreshments for participants | D16: 27000 | E16: =H16*D16 -> 810000 | F16: Food and drinks | H16: 30 | I16: TZS - Tanzanian Shilling | J16: =$E10 -> 0.000438 | K16: =IF(E16="",0,E16*$E10) -> 354.78
A17: Participants transport | C17: Transport support for participants | D17: 27000 | E17: =H17*D17 -> 810000 | F17: Transport | H17: 30 | I17: TZS - Tanzanian Shilling | J17: =$E10 -> 0.000438 | K17: =IF(E17="",0,E17*$E10) -> 354.78
A18: Facilitator fees | C18: Trainer / facilitator fee | D18: 100000 | E18: =H18*D18 -> 300000 | F18: Facilitators(3) | H18: 3 | I18: TZS - Tanzanian Shilling | J18: =$E10 -> 0.000438 | K18: =IF(E18="",0,E18*$E10) -> 131.4
A19: Equipment rent(Camera, Projector) | C19: Equpment rent like projector, camera and laptops | D19: 250000 | E19: =H19*D19 -> 250000 | F19: Equpment | H19: 1 | I19: TZS - Tanzanian Shilling | J19: =$E10 -> 0.000438 | K19: =IF(E19="",0,E19*$E10) -> 109.5
A20: Training materials and Communication | C20: Printed handouts and stationery | D20: 200000 | E20: =H20*D20 -> 200000 | F20: Materials | H20: 1 | I20: TZS - Tanzanian Shilling | J20: =$E10 -> 0.000438 | K20: =IF(E20="",0,E20*$E10) -> 87.6
A21: Internet package | D21: 70000 | E21: =H21*D21 -> 70000 | F21: Internet/Supplies | H21: 1 | I21: TZS - Tanzanian Shilling | J21: =$E10 -> 0.000438 | K21: =IF(E21="",0,E21*$E10) -> 30.66
A22: Bank charges | D22: 30000 | E22: =H22*D22 -> 30000 | H22: 1
A23: You wish to be reimbursed in : | E23: =SUM(E15:E22) -> 2710000 | F23: USD | K23: =SUM(K15:K22) -> 1173.84
A24: ★ Blue cells = fill in your data. Conversion rate auto-applies. Update xe.com rate before submission.

Sheet Aug25 Monthly Edit-a-thon
A2: ◀ BACK TO DASHBOARD | E2: ◀ BACK TO INDEX
A3: Project | E3: Wiki Monthly Edit-a-thon
A4: Activity | E4: Monthly In-Person Edit-a-thon — August 2025
A5: Date of event | E5: August 2025 | I5: Status | K5: Completed
A6: Venue
A7: No. of Participants | E7: Prepared by
A9: Payment details
A10: Conversion rate (xe.com) | E10: 0.000438
A12: Expense details
A13: Date of conversion: | E13: [Enter date currency was converted]
A14: Description | C14: Comments | D14: Cost of unit in Local currency | E14: Cost (in local currency) | F14: Expense type | G14: Receipt? | H14: Number of Unit | I14: Local currency (please select) | J14: Conversion rate (if known) | K14: Receipt converted to USD
A15: Food and drinks | C15: Refreshments for participants | D15: 27000 | E15: =D15*H15 -> 864000 | F15: Food and drinks | H15: 32 | I15: TZS - Tanzanian Shilling | J15: =$E10 -> 0.000438 | K15: =IF(E15="",0,E15*$E10) -> 378.432
A16: Venue / Room Hire | C16: Venue hire for the event | D16: 8000 | E16: =D16*H16 -> 256000 | F16: Venue | H16: 32 | I16: TZS - Tanzanian Shilling | J16: =$E10 -> 0.000438 | K16: =IF(E16="",0,E16*$E10) -> 112.128
A17: Participants transport | C17: Transport support for participants | D17: 27000 | E17: =D17*H17 -> 864000 | F17: Transport | H17: 32 | I17: TZS - Tanzanian Shilling | J17: =$E10 -> 0.000438 | K17: =IF(E17="",0,E17*$E10) -> 378.432
A18: Facilitator fees | C18: Trainer / facilitator fee | D18: 100000 | E18: =D18*H18 -> 300000 | F18: Facilitators(3) | H18: 3 | I18: TZS - Tanzanian Shilling | J18: =$E10 -> 0.000438 | K18: =IF(E18="",0,E18*$E10) -> 131.4
A19: Equipment rent(Camera, Projector) | C19: Equpment rent like projector, camera and laptops | D19: 200000 | E19: =D19*H19 -> 200000 | F19: Equpment | H19: 1 | I19: TZS - Tanzanian Shilling | J19: =$E10 -> 0.000438 | K19: =IF(E19="",0,E19*$E10) -> 87.6
A20: Training materials and Communication | C20: Printed handouts and stationery | D20: 40000 | E20: =D20*H20 -> 40000 | F20: Materials | H20: 1 | I20: TZS - Tanzanian Shilling | J20: =$E10 -> 0.000438 | K20: =IF(E20="",0,E20*$E10) -> 17.52
A21: Internet package | D21: 70000 | E21: =D21*H21 -> 70000 | F21: Internet/Supplies | H21: 1 | I21: TZS - Tanzanian Shilling | J21: =$E10 -> 0.000438 | K21: =IF(E21="",0,E21*$E10) -> 30.66
A22: Bank charges | C22: Bank charges | D22: 30000 | E22: =D22*H22 -> 30000 | H22: 1 | I22: TZS - Tanzanian Shilling | J22: =$E10 -> 0.000438 | K22: =IF(E22="",0,E22*$E10) -> 13.14
A23: You wish to be reimbursed in : | E23: =SUM(E16:E22) -> 1760000 | F23: USD | K23: =SUM(K15:K22) -> 1149.312
A24: ★ Blue cells = fill in your data. Conversion rate auto-applies. Update xe.com rate before submission.

Sheet Oct25 Monthly Edit-a-thon
A1: WIKIMEDIA COMMUNITY KILIMANJARO —ACTIVITY EXPENSE REPORT
A2: ◀ BACK TO DASHBOARD | E2: ◀ BACK TO INDEX
A3: Project | E3: Wiki Monthly Edit-a-thon
A4: Activity | E4: Monthly In-Person Edit-a-thon — October 2025
A5: Date of event | E5: October 2025 | I5: Status | K5: Completed
A6: Venue
A7: No. of Participants | E7: Prepared by
A9: Payment details
A10: Conversion rate (xe.com) | E10: 0.000438
A12: Expense details
A13: Date of conversion: | E13: [Enter date currency was converted]
A14: Description | C14: Comments | E14: Cost (in local currency) | F14: Expense type | G14: Receipt? | I14: Local currency (please select) | J14: Conversion rate (if known) | K14: Receipt converted to USD
A15: Venue / Room Hire | C15: Venue hire for the event | D15: 8000 | E15: =H15*D15 -> 240000 | F15: Venue | H15: 30 | I15: TZS - Tanzanian Shilling | J15: =$E10 -> 0.000438 | K15: =IF(E15="",0,E15*$E10) -> 105.12
A16: Food and drinks | C16: Refreshments for participants | D16: 27000 | E16: =H16*D16 -> 810000 | F16: Food and drinks | H16: 30 | I16: TZS - Tanzanian Shilling | J16: =$E10 -> 0.000438 | K16: =IF(E16="",0,E16*$E10) -> 354.78
A17: Participants transport | C17: Transport support for participants | D17: 27000 | E17: =H17*D17 -> 810000 | F17: Transport | H17: 30 | I17: TZS - Tanzanian Shilling | J17: =$E10 -> 0.000438 | K17: =IF(E17="",0,E17*$E10) -> 354.78
A18: Facilitator fees | C18: Trainer / facilitator fee | D18: 100000 | E18: =H18*D18 -> 300000 | F18: Facilitators(3) | H18: 3 | I18: TZS - Tanzanian Shilling | J18: =$E10 -> 0.000438 | K18: =IF(E18="",0,E18*$E10) -> 131.4
A19: Equipment rent(Camera, Projector) | C19: Equpment rent like projector, camera and laptops | D19: 250000 | E19: =H19*D19 -> 250000 | F19: Equpment | H19: 1 | I19: TZS - Tanzanian Shilling | J19: =$E10 -> 0.000438 | K19: =IF(E19="",0,E19*$E10) -> 109.5
A20: Training materials and Communication | C20: Printed handouts and stationery | D20: 50000 | E20: =H20*D20 -> 50000 | F20: Materials | H20: 1 | I20: TZS - Tanzanian Shilling | J20: =$E10 -> 0.000438 | K20: =IF(E20="",0,E20*$E10) -> 21.9
A21: Internet package | D21: 70000 | E21: =H21*D21 -> 70000 | F21: Internet/Supplies | H21: 1 | I21: TZS - Tanzanian Shilling | J21: =$E10 -> 0.000438 | K21: =IF(E21="",0,E21*$E10) -> 30.66
A22: Bank charges | D22: 30000 | E22: =H22*D22 -> 30000 | H22: 1 | I22: TZS - Tanzanian Shilling | J22: =$E10 -> 0.000438 | K22: =IF(E22="",0,E22*$E10) -> 13.14
A23: You wish to be reimbursed in : | E23: =SUM(E15:E22) -> 2560000 | F23: USD | K23: =SUM(K15:K22) -> 1121.28
A24: ★ Blue cells = fill in your data. Conversion rate auto-applies. Update xe.com rate before submission.

Sheet Dec25 Monthly Edit-a-thon
A1: WIKIMEDIA COMMUNITY KILIMANJARO —ACTIVITY EXPENSE REPORT
A2: ◀ BACK TO DASHBOARD | E2: ◀ BACK TO INDEX
A3: Project | E3: Wiki Monthly Edit-a-thon
A4: Activity | E4: Monthly In-Person Edit-a-thon — December 2025
A5: Date of event | E5: 20.12.2025 | I5: Status | K5: Completed
A6: Venue
A7: No. of Participants | E7: Prepared by
A9: Payment details
A10: Conversion rate (xe.com) | E10: 0.000413
A12: Expense details
A13: Date of conversion: | E13: [Enter date currency was converted]
A14: Description | C14: Comments | E14: Cost (in local currency) | F14: Expense type | G14: Receipt? | I14: Local currency (please select) | J14: Conversion rate (if known) | K14: Receipt converted to USD
A15: Venue / Room Hire | C15: Venue hire for the event | D15: 8000 | E15: =H15*D15 -> 280000 | F15: Venue | H15: 35 | I15: TZS - Tanzanian Shilling | J15: =$E10 -> 0.000413 | K15: =IF(E15="",0,E15*$E10) -> 115.64
A16: Food and drinks | C16: Refreshments for participants | D16: 27000 | E16: =H16*D16 -> 945000 | F16: Food and drinks | H16: 35 | I16: TZS - Tanzanian Shilling | J16: =$E10 -> 0.000413 | K16: =IF(E16="",0,E16*$E10) -> 390.285
A17: Participants transport | C17: Transport support for participants | D17: 27000 | E17: =H17*D17 -> 945000 | F17: Transport | H17: 35 | I17: TZS - Tanzanian Shilling | J17: =$E10 -> 0.000413 | K17: =IF(E17="",0,E17*$E10) -> 390.285
A18: Facilitator fees | C18: Trainer / facilitator fee | D18: 100000 | E18: =H18*D18 -> 300000 | F18: Facilitators(3) | H18: 3 | I18: TZS - Tanzanian Shilling | J18: =$E10 -> 0.000413 | K18: =IF(E18="",0,E18*$E10) -> 123.9
A19: Equipment rent(Camera, Projector) | C19: Equpment rent like projector, camera and laptops | D19: 250000 | E19: =H19*D19 -> 250000 | F19: Equpment | H19: 1 | I19: TZS - Tanzanian Shilling | J19: =$E10 -> 0.000413 | K19: =IF(E19="",0,E19*$E10) -> 103.25
A20: Training materials and Communication | C20: Printed handouts and stationery | D20: 30000 | E20: =H20*D20 -> 30000 | F20: Materials | H20: 1 | I20: TZS - Tanzanian Shilling | J20: =$E10 -> 0.000413 | K20: =IF(E20="",0,E20*$E10) -> 12.39
A21: Internet package | D21: 70000 | E21: =H21*D21 -> 70000 | F21: Internet/Supplies | H21: 1 | I21: TZS - Tanzanian Shilling | J21: =$E10 -> 0.000413 | K21: =IF(E21="",0,E21*$E10) -> 28.91
A22: Bank charges | D22: 30000 | E22: =H22*D22 -> 30000 | H22: 1 | I22: TZS - Tanzanian Shilling | J22: =$E10 -> 0.000413 | K22: =IF(E22="",0,E22*$E10) -> 12.39
A23: You wish to be reimbursed in : | E23: =SUM(E15:E22) -> 2850000 | F23: USD | K23: =SUM(K15:K22) -> 1177.05
A24: ★ Blue cells = fill in your data. Conversion rate auto-applies. Update xe.com rate before submission.

Sheet Oct25 Wikimalkia Training
A1: WIKIMEDIA COMMUNITY KILIMANJARO —ACTIVITY EXPENSE REPORT
A2: ◀ BACK TO DASHBOARD | E2: ◀ BACK TO INDEX
A3: Project | E3: Wikimalkia
A4: Activity | E4: Wikimalkia Training — October 2025
A5: Date of event | E5: October 2025 | I5: Status | K5: Completed
A6: Venue
A7: No. of Participants | E7: Prepared by
A9: Payment details
A10: Conversion rate (xe.com) | E10: 0.000438
A12: Expense details
A13: Date of conversion: | E13: [Enter date currency was converted]
A14: Description | C14: Comments | E14: Cost (in local currency) | F14: Expense type | G14: Receipt? | I14: Local currency (please select) | J14: Conversion rate (if known) | K14: Receipt converted to USD
A15: Venue / Room Hire | C15: Venue hire for the event | D15: 8000 | E15: =H15*D15 -> 240000 | F15: Venue | H15: 30 | I15: TZS - Tanzanian Shilling | J15: =$E10 -> 0.000438 | K15: =IF(E15="",0,E15*$E10) -> 105.12
A16: Food and drinks | C16: Refreshments for participants | D16: 27000 | E16: =H16*D16 -> 810000 | F16: Food and drinks | H16: 30 | I16: TZS - Tanzanian Shilling | J16: =$E10 -> 0.000438 | K16: =IF(E16="",0,E16*$E10) -> 354.78
A17: Participants transport | C17: Transport support for participants | D17: 27000 | E17: =H17*D17 -> 810000 | F17: Transport | H17: 30 | I17: TZS - Tanzanian Shilling | J17: =$E10 -> 0.000438 | K17: =IF(E17="",0,E17*$E10) -> 354.78
A18: Facilitator fees | C18: Trainer / facilitator fee | D18: 100000 | E18: =H18*D18 -> 300000 | F18: Facilitators(3) | H18: 3 | I18: TZS - Tanzanian Shilling | J18: =$E10 -> 0.000438 | K18: =IF(E18="",0,E18*$E10) -> 131.4
A19: Equipment rent(Camera, Projector) | C19: Equpment rent like projector, camera and laptops | D19: 200000 | E19: =H19*D19 -> 200000 | F19: Equpment | H19: 1 | I19: TZS - Tanzanian Shilling | J19: =$E10 -> 0.000438 | K19: =IF(E19="",0,E19*$E10) -> 87.6
A20: Training materials and Communication | C20: Printed handouts and stationery | D20: 35000 | E20: =H20*D20 -> 35000 | F20: Materials | H20: 1 | I20: TZS - Tanzanian Shilling | J20: =$E10 -> 0.000438 | K20: =IF(E20="",0,E20*$E10) -> 15.33
A21: Internet package | D21: 70000 | E21: =H21*D21 -> 70000 | F21: Internet/Supplies | H21: 1 | I21: TZS - Tanzanian Shilling | J21: =$E10 -> 0.000438 | K21: =IF(E21="",0,E21*$E10) -> 30.66
A22: Bank charges | D22: 30000 | E22: =H22*D22 -> 30000 | H22: 1 | J22: =$E10 -> 0.000438 | K22: =IF(E22="",0,E22*$E10) -> 13.14
A23: You wish to be reimbursed in : | E23: =SUM(E15:E22) -> 2495000 | F23: USD | K23: =SUM(K15:K22) -> 1092.81
A24: ★ Blue cells = fill in your data. Conversion rate auto-applies. Update xe.com rate before submission.

Sheet Dec25 Wikimalkia Edit-a-thon
A1: WIKIMEDIA COMMUNITY KILIMANJARO — ACTIVITY EXPENSE REPORT
A2: ◀ BACK TO DASHBOARD | E2: ◀ BACK TO INDEX
A3: Project | E3: Wikimalkia
A4: Activity | E4: Wikimalkia Edit-a-thon — December 2025
A5: Date of event | E5: December 2025 | I5: Status | K5: Completed
A6: Venue
A7: No. of Participants | E7: Prepared by
A9: Payment details
A10: Conversion rate (xe.com) | E10: 0.000438
A12: Expense details
A13: Date of conversion: | E13: [Enter date currency was converted]
A14: Description | C14: Comments | E14: Cost (in local currency) | F14: Expense type | G14: Receipt? | I14: Local currency (please select) | J14: Conversion rate (if known) | K14: Receipt converted to USD
A15: Venue / Room Hire | C15: Venue hire for the event | D15: 8000 | E15: =H15*D15 -> 240000 | F15: Venue | H15: 30 | I15: TZS - Tanzanian Shilling | J15: =$E10 -> 0.000438 | K15: =IF(E15="",0,E15*$E10) -> 105.12
A16: Food and drinks | C16: Refreshments for participants | D16: 27000 | E16: =H16*D16 -> 810000 | F16: Food and drinks | H16: 30 | I16: TZS - Tanzanian Shilling | J16: =$E10 -> 0.000438 | K16: =IF(E16="",0,E16*$E10) -> 354.78
A17: Participants transport | C17: Transport support for participants | D17: 27000 | E17: =H17*D17 -> 810000 | F17: Transport | H17: 30 | I17: TZS - Tanzanian Shilling | J17: =$E10 -> 0.000438 | K17: =IF(E17="",0,E17*$E10) -> 354.78
A18: Facilitator fees | C18: Trainer / facilitator fee | D18: 100000 | E18: =H18*D18 -> 300000 | F18: Facilitators(3) | H18: 3 | I18: TZS - Tanzanian Shilling | J18: =$E10 -> 0.000438 | K18: =IF(E18="",0,E18*$E10) -> 131.4
A19: Equipment rent(Camera, Projector) | C19: Equpment rent like projector, camera and laptops | D19: 250000 | E19: =H19*D19 -> 250000 | F19: Equpment | H19: 1 | I19: TZS - Tanzanian Shilling | J19: =$E10 -> 0.000438 | K19: =IF(E19="",0,E19*$E10) -> 109.5
A20: Training materials and Communication | C20: Printed handouts and stationery | D20: 40000 | E20: =H20*D20 -> 40000 | F20: Materials | H20: 1 | I20: TZS - Tanzanian Shilling | J20: =$E10 -> 0.000438 | K20: =IF(E20="",0,E20*$E10) -> 17.52
A21: Internet package | D21: 70000 | E21: =H21*D21 -> 70000 | F21: Internet/Supplies | H21: 1 | I21: TZS - Tanzanian Shilling | J21: =$E10 -> 0.000438 | K21: =IF(E21="",0,E21*$E10) -> 30.66
A22: Bank charges | D22: 30000 | E22: =H22*D22 -> 30000 | H22: 1 | I22: TZS - Tanzanian Shilling | J22: =$E10 -> 0.000438 | K22: =IF(E22="",0,E22*$E10) -> 13.14
A23: You wish to be reimbursed in : | E23: =SUM(E15:E22) -> 2550000 | F23: USD | K23: =SUM(K15:K22) -> 1116.9
A24: ★ Blue cells = fill in your data. Conversion rate auto-applies. Update xe.com rate before submission.

Sheet Nov25 Error Fix Workshop
A1: WIKIMEDIA COMMUNITY KILIMANJARO — ACTIVITY EXPENSE REPORT
A2: ◀ BACK TO DASHBOARD | E2: ◀ BACK TO INDEX
A3: Project | E3: Error, Fix and Contribute
A4: Activity | E4: Error, Fix and Contribute Workshop — November 2025
A5: Date of event | E5: November 2025 | I5: Status | K5: Completed
A6: Venue
A7: No. of Participants | E7: Prepared by
A9: Payment details
A10: Conversion rate (xe.com) | E10: 0.000438
A12: Expense details
A13: Date of conversion: | E13: [Enter date currency was converted]
A14: Description | C14: Comments | E14: Cost (in local currency) | F14: Expense type | G14: Receipt? | I14: Local currency (please select) | J14: Conversion rate (if known) | K14: Receipt converted to USD
A15: Venue / Room Hire | C15: Venue hire for the event | D15: 8000 | E15: =H15*D15 -> 280000 | F15: Venue | H15: 35 | I15: TZS - Tanzanian Shilling | J15: =$E10 -> 0.000438 | K15: =IF(E15="",0,E15*$E10) -> 122.64
A16: Food and drinks | C16: Refreshments for participants | D16: 27000 | E16: =H16*D16 -> 945000 | F16: Food and drinks | H16: 35 | I16: TZS - Tanzanian Shilling | J16: =$E10 -> 0.000438 | K16: =IF(E16="",0,E16*$E10) -> 413.91
A17: Participants transport | C17: Transport support for participants | D17: 27000 | E17: =H17*D17 -> 945000 | F17: Transport | H17: 35 | I17: TZS - Tanzanian Shilling | J17: =$E10 -> 0.000438 | K17: =IF(E17="",0,E17*$E10) -> 413.91
A18: Facilitator fees | C18: Trainer / facilitator fee | D18: 100000 | E18: =H18*D18 -> 300000 | F18: Facilitators(3) | H18: 3 | I18: TZS - Tanzanian Shilling | J18: =$E10 -> 0.000438 | K18: =IF(E18="",0,E18*$E10) -> 131.4
A19: Equipment rent(Camera, Projector) | C19: Equpment rent like projector, camera and laptops | D19: 250000 | E19: =H19*D19 -> 250000 | F19: Equpment | H19: 1 | I19: TZS - Tanzanian Shilling | J19: =$E10 -> 0.000438 | K19: =IF(E19="",0,E19*$E10) -> 109.5
A20: Training materials and Communication | C20: Printed handouts and stationery | D20: 45000 | E20: =H20*D20 -> 45000 | F20: Materials | H20: 1 | I20: TZS - Tanzanian Shilling | J20: =$E10 -> 0.000438 | K20: =IF(E20="",0,E20*$E10) -> 19.71
A21: Internet package | D21: 70000 | E21: =H21*D21 -> 70000 | F21: Internet/Supplies | H21: 1 | I21: TZS - Tanzanian Shilling | J21: =$E10 -> 0.000438 | K21: =IF(E21="",0,E21*$E10) -> 30.66
A22: Bank charges | D22: 30000 | E22: =H22*D22 -> 30000 | H22: 1 | I22: TZS - Tanzanian Shilling | J22: =$E10 -> 0.000438 | K22: =IF(E22="",0,E22*$E10) -> 13.14
A23: You wish to be reimbursed in : | E23: =SUM(E15:E22) -> 2865000 | F23: USD | K23: =SUM(K15:K22) -> 1254.87
A24: ★ Blue cells = fill in your data. Conversion rate auto-applies. Update xe.com rate before submission.

Sheet Jan26 Error Fix Training
A1: WIKIMEDIA COMMUNITY KILIMANJARO — ACTIVITY EXPENSE REPORT
A2: ◀ BACK TO DASHBOARD | E2: ◀ BACK TO INDEX
A3: Project | E3: Error, Fix and Contribute
A4: Activity | E4: Error, Fix and Contribute Training — January 2026
A5: Date of event | E5: January 2026 | I5: Status | K5: Completed
A6: Venue
A7: No. of Participants | E7: Prepared by
A9: Payment details
A10: Conversion rate (xe.com) | E10: 0.000438
A12: Expense details
A13: Date of conversion: | E13: [Enter date currency was converted]
A14: Description | C14: Comments | E14: Cost (in local currency) | F14: Expense type | G14: Receipt? | I14: Local currency (please select) | J14: Conversion rate (if known) | K14: Receipt converted to USD
A15: Venue / Room Hire | C15: Venue hire for the event | D15: 8000 | E15: =H15*D15 -> 280000 | F15: Venue | H15: 35 | I15: TZS - Tanzanian Shilling | J15: =$E10 -> 0.000438 | K15: =IF(E15="",0,E15*$E10) -> 122.64
A16: Food and drinks | C16: Refreshments for participants | D16: 27000 | E16: =H16*D16 -> 945000 | F16: Food and drinks | H16: 35 | I16: TZS - Tanzanian Shilling | J16: =$E10 -> 0.000438 | K16: =IF(E16="",0,E16*$E10) -> 413.91
A17: Participants transport | C17: Transport support for participants | D17: 27000 | E17: =H17*D17 -> 945000 | F17: Transport | H17: 35 | I17: TZS - Tanzanian Shilling | J17: =$E10 -> 0.000438 | K17: =IF(E17="",0,E17*$E10) -> 413.91
A18: Facilitator fees | C18: Trainer / facilitator fee | D18: 100000 | E18: =H18*D18 -> 300000 | F18: Facilitators(3) | H18: 3 | I18: TZS - Tanzanian Shilling | J18: =$E10 -> 0.000438 | K18: =IF(E18="",0,E18*$E10) -> 131.4
A19: Equipment rent(Camera, Projector) | C19: Equpment rent like projector, camera and laptops | D19: 250000 | E19: =H19*D19 -> 250000 | F19: Equpment | H19: 1 | I19: TZS - Tanzanian Shilling | J19: =$E10 -> 0.000438 | K19: =IF(E19="",0,E19*$E10) -> 109.5
A20: Training materials and Communication | C20: Printed handouts and stationery | D20: 35000 | E20: =H20*D20 -> 35000 | F20: Materials | H20: 1 | I20: TZS - Tanzanian Shilling | J20: =$E10 -> 0.000438 | K20: =IF(E20="",0,E20*$E10) -> 15.33
A21: Internet package | D21: 70000 | E21: =H21*D21 -> 70000 | F21: Internet/Supplies | H21: 1 | I21: TZS - Tanzanian Shilling | J21: =$E10 -> 0.000438 | K21: =IF(E21="",0,E21*$E10) -> 30.66
A22: Bank charges | D22: 30000 | E22: =H22*D22 -> 30000 | H22: 1 | I22: TZS - Tanzanian Shilling | J22: =$E10 -> 0.000438 | K22: =IF(E22="",0,E22*$E10) -> 13.14
A23: You wish to be reimbursed in : | E23: =SUM(E15:E22) -> 2855000 | F23: USD | K23: =SUM(K15:K22) -> 1250.49
A24: ★ Blue cells = fill in your data. Conversion rate auto-applies. Update xe.com rate before submission.

Sheet Lets Connect Event 1
A1: WIKIMEDIA COMMUNITY TANZANIA — ACTIVITY EXPENSE REPORT
A2: ◀ BACK TO DASHBOARD | D2: ◀ BACK TO INDEX
A3: Project | D3: Let's Connect
A4: Activity | D4: Let's Connect: Inclusive Collaboration Space — Event 1 of 2
A5: Date of event | D5: [Date of Event 1] | G5: Status | I5: Completed
A6: Venue
A7: No. of Participants | D7: Prepared by
A9: Payment details
A10: Conversion rate (xe.com) | D10: 0.000438
A12: Expense details
A13: Date of conversion: | D13: [Enter date currency was converted]
A14: Description | C14: Comments | D14: Cost (in local currency) | E14: Expense type | F14: Receipt? | G14: Local currency (please select) | H14: Conversion rate (if known) | I14: Receipt converted to USD
A15: Venue / Room Hire | C15: Venue hire for the event | D15: 1000000 | E15: Venue | G15: TZS - Tanzanian Shilling | H15: =$D10 -> 0.000438 | I15: =IF(D15="",0,D15*$D10) -> 438
A16: Food and drinks | C16: Refreshments for participants | D16: 700000 | E16: Food and drinks | G16: TZS - Tanzanian Shilling | H16: =$D10 -> 0.000438 | I16: =IF(D16="",0,D16*$D10) -> 306.6
A17: Participants transport | C17: Transport support for participants | D17: 1000000 | E17: Transport | G17: TZS - Tanzanian Shilling | H17: =$D10 -> 0.000438 | I17: =IF(D17="",0,D17*$D10) -> 438
A18: Facilitator fees | C18: Trainer / facilitator fee | D18: 400000 | E18: Facilitator | G18: TZS - Tanzanian Shilling | H18: =$D10 -> 0.000438 | I18: =IF(D18="",0,D18*$D10) -> 175.2
A19: Training materials | C19: (Camera rent) | D19: 100000 | E19: Materials | G19: TZS - Tanzanian Shilling | H19: =$D10 -> 0.000438 | I19: =IF(D19="",0,D19*$D10) -> 43.8
A20: Internet package | E20: Internet/Supplies | G20: TZS - Tanzanian Shilling | H20: =$D10 -> 0.000438 | I20: =IF(D20="",0,D20*$D10) -> 0
A21: Bank charges | D21: 30000 | G21: TZS - Tanzanian Shilling | H21: =$D10 -> 0.000438 | I21: =IF(D21="",0,D21*$D10) -> 13.14
A22: You wish to be reimbursed in : | D22: =SUM(D15:D21) -> 3230000 | E22: USD | I22: =SUM(I15:I21) -> 1414.74
A23: ★ Blue cells = fill in your data. Conversion rate auto-applies. Update xe.com rate before submission.

Sheet Kiwix for shool-program
A1: WIKIMEDIA COMMUNITY TANZANIA — ACTIVITY EXPENSE REPORT
A2: ◀ BACK TO DASHBOARD
A3: Project | D3: Kiwix for School program
A4: Activity | D4: Kiwix for School program (from august to september)
A5: Date of event | G5: Status | I5: Completed
A6: Venue
A7: No. of Participants
A9: Payment details
A10: Conversion rate (xe.com) | D10: 0.000438
A12: Expense details
A13: Date of conversion: | D13: [Enter date currency was converted]
A14: Description | C14: Comments | D14: Cost (in local currency) | E14: Expense type | F14: Receipt? | G14: Local currency (please select) | H14: Conversion rate (if known) | I14: Receipt converted to USD
A15: Stipend for Trainers | C15: The amount help to pay four trainers (Transport to schools and refresment) | D15: 2300000 | E15: Trainers for different school | G15: TZS - Tanzanian Shilling | H15: 0.0004138 | I15: =IF(D15="",0,D15*$H15) -> 951.74
D16: 0 | G16: TZS - Tanzanian Shilling | H16: 0.0004138 | I16: =IF(D16="",0,D16*$H16) -> 0
D17: 0 | G17: TZS - Tanzanian Shilling | H17: 0.0004138 | I17: =IF(D17="",0,D17*$H17) -> 0
D18: 0 | G18: TZS - Tanzanian Shilling | H18: 0.0004138 | I18: =IF(D18="",0,D18*$H18) -> 0
D19: 0 | G19: TZS - Tanzanian Shilling | H19: 0.0004138 | I19: =IF(D19="",0,D19*$H19) -> 0
D20: 0 | G20: TZS - Tanzanian Shilling | H20: 0.0004138 | I20: =IF(D20="",0,D20*$H20) -> 0
H21: 0.0004138 | I21: =IF(D21="",0,D21*$H21) -> 0
A22: You wish to be reimbursed in : | D22: 0 | E22: USD | I22: =SUM(I15:I21) -> 951.74
A23: ★ Blue cells = fill in your data. Conversion rate auto-applies. Update xe.com rate before submission.

Sheet Mar26 Monthly Edit-a-thon
A1: WIKIMEDIA COMMUNITY TANZANIA — ACTIVITY EXPENSE REPORT
A2: ◀ BACK TO DASHBOARD | E2: ◀ BACK TO INDEX
A3: Project | E3: Wiki Monthly Edit-a-thon
A4: Activity | E4: Monthly In-Person Edit-a-thon — March 2026
A5: Date of event | E5: March 2026 | I5: Status | K5: Planned
A6: Venue
A7: No. of Participants | E7: Prepared by
A9: Payment details
A10: Conversion rate (xe.com) | E10: 0.000413
A12: Expense details
A13: Date of conversion: | E13: [Enter date currency was converted]
A14: Description | C14: Comments | E14: Cost (in local currency) | F14: Expense type | G14: Receipt? | I14: Local currency (please select) | J14: Conversion rate (if known) | K14: Receipt converted to USD
A15: Venue / Room Hire | C15: Venue hire for the event | E15: 0 | F15: Venue | I15: TZS - Tanzanian Shilling | J15: =$E10 -> 0.000413 | K15: =IF(E15="",0,E15*$E10) -> 0
A16: Food and drinks | C16: Refreshments for participants | E16: 0 | F16: Food and drinks | I16: TZS - Tanzanian Shilling | J16: =$E10 -> 0.000413 | K16: =IF(E16="",0,E16*$E10) -> 0
A17: Participants transport | C17: Transport support for participants | E17: 0 | F17: Transport | I17: TZS - Tanzanian Shilling | J17: =$E10 -> 0.000413 | K17: =IF(E17="",0,E17*$E10) -> 0
A18: Facilitator fees | C18: Trainer / facilitator fee | E18: 0 | F18: Facilitator | I18: TZS - Tanzanian Shilling | J18: =$E10 -> 0.000413 | K18: =IF(E18="",0,E18*$E10) -> 0
A19: Training materials | C19: Printed handouts and stationery | E19: 0 | F19: Materials | I19: TZS - Tanzanian Shilling | J19: =$E10 -> 0.000413 | K19: =IF(E19="",0,E19*$E10) -> 0
A20: Internet package | E20: 0 | F20: Internet/Supplies | I20: TZS - Tanzanian Shilling | J20: =$E10 -> 0.000413 | K20: =IF(E20="",0,E20*$E10) -> 0
A21: Bank charges
A23: You wish to be reimbursed in : | E23: =SUM(E15:E21) -> 0 | F23: USD | K23: =SUM(K15:K21) -> 0
A24: ★ Blue cells = fill in your data. Conversion rate auto-applies. Update xe.com rate before submission.

Sheet Feb26 Wikimalkia Workshop
A1: WIKIMEDIA COMMUNITY KILIMANJARO — ACTIVITY EXPENSE REPORT
A2: ◀ BACK TO DASHBOARD | E2: ◀ BACK TO INDEX
A3: Project | E3: Wikimalkia
A4: Activity | E4: Wikimalkia Workshop — February 2026
A5: Date of event | E5: February 2026 | I5: Status | K5: Copleted
A6: Venue
A7: No. of Participants | E7: Prepared by
A9: Payment details
A10: Conversion rate (xe.com) | E10: 0.000438
A12: Expense details
A13: Date of conversion: | E13: [Enter date currency was converted]
A14: Description | C14: Comments | E14: Cost (in local currency) | F14: Expense type | G14: Receipt? | I14: Local currency (please select) | J14: Conversion rate (if known) | K14: Receipt converted to USD
A15: Venue / Room Hire | C15: Venue hire for the event | D15: 200000 | E15: =H15*D15 -> 200000 | F15: Venue | H15: 1 | I15: TZS - Tanzanian Shilling | J15: =$E10 -> 0.000438 | K15: =IF(E15="",0,E15*$E10) -> 87.6
A16: Food and drinks | C16: Refreshments for participants | D16: 27000 | E16: =H16*D16 -> 810000 | F16: Food and drinks | H16: 30 | I16: TZS - Tanzanian Shilling | J16: =$E10 -> 0.000438 | K16: =IF(E16="",0,E16*$E10) -> 354.78
A17: Participants transport | C17: Transport support for participants | D17: 27000 | E17: =H17*D17 -> 810000 | F17: Transport | H17: 30 | I17: TZS - Tanzanian Shilling | J17: =$E10 -> 0.000438 | K17: =IF(E17="",0,E17*$E10) -> 354.78
A18: Facilitator fees | C18: Trainer / facilitator fee | D18: 100000 | E18: =H18*D18 -> 400000 | F18: Facilitators(3) | H18: 4 | I18: TZS - Tanzanian Shilling | J18: =$E10 -> 0.000438 | K18: =IF(E18="",0,E18*$E10) -> 175.2
A19: Equipment rent(Camera, Projector) | C19: Equpment rent like projector, camera and laptops | D19: 250000 | E19: =H19*D19 -> 250000 | F19: Equpment | H19: 1 | I19: TZS - Tanzanian Shilling | J19: =$E10 -> 0.000438 | K19: =IF(E19="",0,E19*$E10) -> 109.5
A20: Training materials and Communication | C20: Printed handouts and stationery | D20: 200000 | E20: =H20*D20 -> 200000 | F20: Materials | H20: 1 | I20: TZS - Tanzanian Shilling | J20: =$E10 -> 0.000438 | K20: =IF(E20="",0,E20*$E10) -> 87.6
A21: Internet package | D21: 70000 | E21: =H21*D21 -> 70000 | F21: Internet/Supplies | H21: 1 | I21: TZS - Tanzanian Shilling | J21: =$E10 -> 0.000438 | K21: =IF(E21="",0,E21*$E10) -> 30.66
A22: Bank charges | D22: 30000 | E22: =H22*D22 -> 30000 | H22: 1 | I22: TZS - Tanzanian Shilling | J22: =$E10 -> 0.000438 | K22: =IF(E22="",0,E22*$E10) -> 13.14
A23: You wish to be reimbursed in : | E23: =SUM(E15:E22) -> 2770000 | F23: USD | K23: =SUM(K15:K22) -> 1213.26
A24: ★ Blue cells = fill in your data. Conversion rate auto-applies. Update xe.com rate before submission.

Sheet Apr26 Monthly Edit-a-thon
A1: WIKIMEDIA COMMUNITY KILIMANJARO — ACTIVITY EXPENSE REPORT
A2: ◀ BACK TO DASHBOARD | D2: ◀ BACK TO INDEX
A3: Project | D3: Wiki Monthly Edit-a-thon
A4: Activity | D4: Monthly In-Person Edit-a-thon — April 2026
A5: Date of event | D5: April 2026 | G5: Status | I5: Planned
A6: Venue
A7: No. of Participants | D7: Prepared by
A9: Payment details
A10: Conversion rate (xe.com) | D10: 0.000413
A12: Expense details
A13: Date of conversion: | D13: [Enter date currency was converted]
A14: Description | C14: Comments | D14: Cost (in local currency) | E14: Expense type | F14: Receipt? | G14: Local currency (please select) | H14: Conversion rate (if known) | I14: Receipt converted to USD
A15: Venue / Room Hire | C15: Venue hire for the event | D15: 0 | E15: Venue | G15: TZS - Tanzanian Shilling | H15: =$D10 -> 0.000413 | I15: =IF(D15="",0,D15*$D10) -> 0
A16: Food and drinks | C16: Refreshments for participants | D16: 0 | E16: Food and drinks | G16: TZS - Tanzanian Shilling | H16: =$D10 -> 0.000413 | I16: =IF(D16="",0,D16*$D10) -> 0
A17: Participants transport | C17: Transport support for participants | D17: 0 | E17: Transport | G17: TZS - Tanzanian Shilling | H17: =$D10 -> 0.000413 | I17: =IF(D17="",0,D17*$D10) -> 0
A18: Facilitator fees | C18: Trainer / facilitator fee | D18: 0 | E18: Facilitator | G18: TZS - Tanzanian Shilling | H18: =$D10 -> 0.000413 | I18: =IF(D18="",0,D18*$D10) -> 0
A19: Training materials | C19: Printed handouts and stationery | D19: 0 | E19: Materials | G19: TZS - Tanzanian Shilling | H19: =$D10 -> 0.000413 | I19: =IF(D19="",0,D19*$D10) -> 0
A20: Internet package | D20: 0 | E20: Internet/Supplies | G20: TZS - Tanzanian Shilling | H20: =$D10 -> 0.000413 | I20: =IF(D20="",0,D20*$D10) -> 0
A21: Bank charges
A22: You wish to be reimbursed in : | D22: =SUM(D15:D21) -> 0 | E22: USD | I22: =SUM(I15:I21) -> 0
A23: ★ Blue cells = fill in your data. Conversion rate auto-applies. Update xe.com rate before submission.

Sheet Feb26 Feminism Folklore
A1: WIKIMEDIA COMMUNITY KILIMANJARO — ACTIVITY EXPENSE REPORT
A2: ◀ BACK TO DASHBOARD | D2: ◀ BACK TO INDEX
A3: Project | D3: Feminism and Folklore
A4: Activity | D4: Feminism and Folklore Edit-a-thon — February 2026
A5: Date of event | D5: February 2026 | G5: Status | I5: Planned
A6: Venue
A7: No. of Participants | D7: Prepared by
A9: Payment details
A10: Conversion rate (xe.com) | D10: 0.000413
A12: Expense details
A13: Date of conversion: | D13: [Enter date currency was converted]
A14: Description | C14: Comments | D14: Cost (in local currency) | E14: Expense type | F14: Receipt? | G14: Local currency (please select) | H14: Conversion rate (if known) | I14: Receipt converted to USD
A15: Venue / Room Hire | C15: Venue hire for the event | D15: 0 | E15: Venue | G15: TZS - Tanzanian Shilling | H15: =$D10 -> 0.000413 | I15: =IF(D15="",0,D15*$D10) -> 0
A16: Food and drinks | C16: Refreshments for participants | D16: 0 | E16: Food and drinks | G16: TZS - Tanzanian Shilling | H16: =$D10 -> 0.000413 | I16: =IF(D16="",0,D16*$D10) -> 0
A17: Participants transport | C17: Transport support for participants | D17: 0 | E17: Transport | G17: TZS - Tanzanian Shilling | H17: =$D10 -> 0.000413 | I17: =IF(D17="",0,D17*$D10) -> 0
A18: Facilitator fees | C18: Trainer / facilitator fee | D18: 0 | E18: Facilitator | G18: TZS - Tanzanian Shilling | H18: =$D10 -> 0.000413 | I18: =IF(D18="",0,D18*$D10) -> 0
A19: Training materials | C19: Printed handouts and stationery | D19: 0 | E19: Materials | G19: TZS - Tanzanian Shilling | H19: =$D10 -> 0.000413 | I19: =IF(D19="",0,D19*$D10) -> 0
A20: Internet package | D20: 0 | E20: Internet/Supplies | G20: TZS - Tanzanian Shilling | H20: =$D10 -> 0.000413 | I20: =IF(D20="",0,D20*$D10) -> 0
A21: Bank charges
A22: You wish to be reimbursed in : | D22: =SUM(D15:D21) -> 0 | E22: USD | I22: =SUM(I15:I21) -> 0
A23: ★ Blue cells = fill in your data. Conversion rate auto-applies. Update xe.com rate before submission.

Sheet Mar26 WCK Training
A1: WIKIMEDIA COMMUNITY KILIMANJARO — ACTIVITY EXPENSE REPORT
A2: ◀ BACK TO DASHBOARD | D2: ◀ BACK TO INDEX
A3: Project | D3: Wikimedia Community Kilimanjaro
A4: Activity | D4: Wikimedia Community Kilimanjaro Training — March 2026
A5: Date of event | D5: March 2026 | G5: Status | I5: Planned
A6: Venue
A7: No. of Participants | D7: Prepared by
A9: Payment details
A10: Conversion rate (xe.com) | D10: 0.000413
A12: Expense details
A13: Date of conversion: | D13: [Enter date currency was converted]
A14: Description | C14: Comments | D14: Cost (in local currency) | E14: Expense type | F14: Receipt? | G14: Local currency (please select) | H14: Conversion rate (if known) | I14: Receipt converted to USD
A15: Venue / Room Hire | C15: Venue hire for the event | D15: 0 | E15: Venue | G15: TZS - Tanzanian Shilling | H15: =$D10 -> 0.000413 | I15: =IF(D15="",0,D15*$D10) -> 0
A16: Food and drinks | C16: Refreshments for participants | D16: 0 | E16: Food and drinks | G16: TZS - Tanzanian Shilling | H16: =$D10 -> 0.000413 | I16: =IF(D16="",0,D16*$D10) -> 0
A17: Participants transport | C17: Transport support for participants | D17: 0 | E17: Transport | G17: TZS - Tanzanian Shilling | H17: =$D10 -> 0.000413 | I17: =IF(D17="",0,D17*$D10) -> 0
A18: Facilitator fees | C18: Trainer / facilitator fee | D18: 0 | E18: Facilitator | G18: TZS - Tanzanian Shilling | H18: =$D10 -> 0.000413 | I18: =IF(D18="",0,D18*$D10) -> 0
A19: Training materials | C19: Printed handouts and stationery | D19: 0 | E19: Materials | G19: TZS - Tanzanian Shilling | H19: =$D10 -> 0.000413 | I19: =IF(D19="",0,D19*$D10) -> 0
A20: Internet package | D20: 0 | E20: Internet/Supplies | G20: TZS - Tanzanian Shilling | H20: =$D10 -> 0.000413 | I20: =IF(D20="",0,D20*$D10) -> 0
A21: Bank charges
A22: You wish to be reimbursed in : | D22: =SUM(D15:D21) -> 0 | E22: USD | I22: =SUM(I15:I21) -> 0
A23: ★ Blue cells = fill in your data. Conversion rate auto-applies. Update xe.com rate before submission.

Sheet Lets Connect Event 2
A1: WIKIMEDIA COMMUNITY KILIMANJARO — ACTIVITY EXPENSE REPORT
A2: ◀ BACK TO DASHBOARD | D2: ◀ BACK TO INDEX
A3: Project | D3: Let's Connect
A4: Activity | D4: Let's Connect: Inclusive Collaboration Space — Event 2 of 2
A5: Date of event | D5: [Date TBD] | G5: Status | I5: Planned
A6: Venue
A7: No. of Participants | D7: Prepared by
A9: Payment details
A10: Conversion rate (xe.com) | D10: 0.000413
A12: Expense details
A13: Date of conversion: | D13: [Enter date currency was converted]
A14: Description | C14: Comments | D14: Cost (in local currency) | E14: Expense type | F14: Receipt? | G14: Local currency (please select) | H14: Conversion rate (if known) | I14: Receipt converted to USD
A15: Venue / Room Hire | C15: Venue hire for the event | D15: 0 | E15: Venue | G15: TZS - Tanzanian Shilling | H15: =$D10 -> 0.000413 | I15: =IF(D15="",0,D15*$D10) -> 0
A16: Food and drinks | C16: Refreshments for participants | D16: 0 | E16: Food and drinks | G16: TZS - Tanzanian Shilling | H16: =$D10 -> 0.000413 | I16: =IF(D16="",0,D16*$D10) -> 0
A17: Participants transport | C17: Transport support for participants | D17: 0 | E17: Transport | G17: TZS - Tanzanian Shilling | H17: =$D10 -> 0.000413 | I17: =IF(D17="",0,D17*$D10) -> 0
A18: Facilitator fees | C18: Trainer / facilitator fee | D18: 0 | E18: Facilitator | G18: TZS - Tanzanian Shilling | H18: =$D10 -> 0.000413 | I18: =IF(D18="",0,D18*$D10) -> 0
A19: Training materials | C19: Printed handouts and stationery | D19: 0 | E19: Materials | G19: TZS - Tanzanian Shilling | H19: =$D10 -> 0.000413 | I19: =IF(D19="",0,D19*$D10) -> 0
A20: Internet package | D20: 0 | E20: Internet/Supplies | G20: TZS - Tanzanian Shilling | H20: =$D10 -> 0.000413 | I20: =IF(D20="",0,D20*$D10) -> 0
A21: Bank charges
A22: You wish to be reimbursed in : | D22: =SUM(D15:D21) -> 0 | E22: USD | I22: =SUM(I15:I21) -> 0
A23: ★ Blue cells = fill in your data. Conversion rate auto-applies. Update xe.com rate before submission.

Sheet May26 WCK Wrap-up
A1: WIKIMEDIA COMMUNITY KILIMANJARO — ACTIVITY EXPENSE REPORT
A2: ◀ BACK TO DASHBOARD | D2: ◀ BACK TO INDEX
A3: Project | D3: Wikimedia Community Kilimanjaro
A4: Activity | D4: Wikimedia Community Kilimanjaro Wrap-up — May 2026
A5: Date of event | D5: May 2026 | G5: Status | I5: Planned
A6: Venue
A7: No. of Participants | D7: Prepared by
A9: Payment details
A10: Conversion rate (xe.com) | D10: 0.000413
A12: Expense details
A13: Date of conversion: | D13: [Enter date currency was converted]
A14: Description | C14: Comments | D14: Cost (in local currency) | E14: Expense type | F14: Receipt? | G14: Local currency (please select) | H14: Conversion rate (if known) | I14: Receipt converted to USD
A15: Venue / Room Hire | C15: Venue hire for the event | D15: 0 | E15: Venue | G15: TZS - Tanzanian Shilling | H15: =$D10 -> 0.000413 | I15: =IF(D15="",0,D15*$D10) -> 0
A16: Food and drinks | C16: Refreshments for participants | D16: 0 | E16: Food and drinks | G16: TZS - Tanzanian Shilling | H16: =$D10 -> 0.000413 | I16: =IF(D16="",0,D16*$D10) -> 0
A17: Participants transport | C17: Transport support for participants | D17: 0 | E17: Transport | G17: TZS - Tanzanian Shilling | H17: =$D10 -> 0.000413 | I17: =IF(D17="",0,D17*$D10) -> 0
A18: Facilitator fees | C18: Trainer / facilitator fee | D18: 0 | E18: Facilitator | G18: TZS - Tanzanian Shilling | H18: =$D10 -> 0.000413 | I18: =IF(D18="",0,D18*$D10) -> 0
A19: Training materials | C19: Printed handouts and stationery | D19: 0 | E19: Materials | G19: TZS - Tanzanian Shilling | H19: =$D10 -> 0.000413 | I19: =IF(D19="",0,D19*$D10) -> 0
A20: Internet package | D20: 0 | E20: Internet/Supplies | G20: TZS - Tanzanian Shilling | H20: =$D10 -> 0.000413 | I20: =IF(D20="",0,D20*$D10) -> 0
A21: Bank charges
A22: You wish to be reimbursed in : | D22: =SUM(D15:D21) -> 0 | E22: USD | I22: =SUM(I15:I21) -> 0
A23: ★ Blue cells = fill in your data. Conversion rate auto-applies. Update xe.com rate before submission.

Sheet 💰 Salary & Stipend
A1: WIKIMEDIA COMMUNITY KILIMANJARO— SALARY TRACKER
A2: 3 staff | Payment date: 25th of every month | Period: July 2025 – July 2026 (13 payments)
A3: ◀ BACK TO DASHBOARD
A5: Conversion rate (xe.com) | C5: 0.0004138 | D5: TZS → USD | Update from xe.com before submission
A7: Role / Staff Member | B7: Pay Date | C7: Jul 2025 | D7: Aug 2025 | E7: Sep 2025 | F7: Oct 2025 | G7: Nov 2025 | H7: Dec 2025 | I7: Jan 2026 | J7: Feb 2026 | K7: Mar 2026 | L7: Apr 2026 | M7: May 2026 | N7: Jun 2026 | O7: Jul 2026 | P7: Total (TZS) | Q7: Conv. Rate | R7: Total (USD)
A8: Program Coordinator | B8: 25th of month | C8: 1933300 | D8: 1933300 | E8: 1933300 | F8: 1933300 | G8: 1933300 | H8: 1933300 | I8: 1933300 | L8: 0 | M8: 0 | N8: 0 | O8: 0 | P8: =SUM(C8:O8) -> 13533100 | Q8: =$C5 -> 0.0004138 | R8: =P8*$C5 -> 5599.9968
A9: Community Manager | B9: 25th of month | C9: 0 | D9: 0 | E9: 0 | F9: 0 | G9: 0 | H9: 0 | I9: 0 | J9: 0 | K9: 0 | L9: 0 | M9: 0 | N9: 0 | O9: 0 | P9: =SUM(C9:O9) -> 0 | Q9: =$C5 -> 0.0004138 | R9: =P9*$C5 -> 0
A10: Social Media Manager | B10: 25th of month | C10: 0 | D10: 0 | E10: 0 | F10: 0 | G10: 0 | H10: 0 | I10: 0 | L10: 0 | M10: 0 | N10: 0 | O10: 0 | P10: =SUM(C10:O10) -> 0 | Q10: =$C5 -> 0.0004138 | R10: =P10*$C5 -> 0
A11: Volunteer Stipend (Four) | B11: 25th of month | C11: 0 | D11: 0 | E11: 0 | F11: 0 | G11: 0 | H11: 0 | I11: 0 | L11: 0 | M11: 0 | N11: 0 | O11: 0 | P11: =SUM(C11:O11) -> 0 | Q11: =$C5 -> 0.0004138 | R11: =P11*$C5 -> 0
A12: Monthly Total (TZS) | C12: =SUM(C8:C11) -> 1933300 | D12: =SUM(D8:D10) -> 1933300 | E12: =SUM(E8:E10) -> 1933300 | F12: =SUM(F8:F10) -> 1933300 | G12: =SUM(G8:G10) -> 1933300 | H12: =SUM(H8:H10) -> 1933300 | I12: =SUM(I8:I10) -> 1933300 | J12: =SUM(J8:J10) -> 0 | K12: =SUM(K8:K10) -> 0 | ... P12: =SUM(P8:P10) -> 13533100 | R12: =SUM(R8:R10) -> 5599.9968
A14: GRAND TOTAL — ALL STAFF (July 2025 – July 2026) | P14: =P12 -> 13533100 | R14: =R12 -> 5599.9968

Sheet 🗂️ Administrative Costs
A1: WIKIMEDIA COMMUNITY KILIMANJARO — ACTIVITY EXPENSE REPORT
A2: Covers ongoing operational costs: social media, communication, internet, printing, bank charges, subscriptions, and other overheads.
A3: Conversion rate (xe.com) | D3: 0.0004138 | G3: TZS → USD | Update from xe.com before submission
A5: # | B5: Item / Description | C5: Comments | D5: Month | E5: Amount (TZS) | F5: Receipt? | G5: Conv. Rate | H5: — | I5: Amount (USD)
A6: 📱 Social Media & Digital Marketing
A7: 1 | B7: Facebook / Instagram Ads | C7: Paid promotion for events | D7: Monthly | E7: 0 | G7: =$D3 -> 0.0004138 | I7: =E7*$D3 -> 0
A8: 2 | B8: Canva Pro Subscription | C8: Design tool for social media posts | D8: Monthly | E8: 0 | G8: =$D3 -> 0.0004138 | I8: =E8*$D3 -> 0
A9: 3 | B9: Content creation fees | C9: Freelance designer / creator | D9: Per project | E9: 0 | G9: =$D3 -> 0.0004138 | I9: =E9*$D3 -> 0
A10: 4 | B10: Social media scheduling tool | C10: Buffer / Hootsuite etc. | D10: Monthly | E10: 0 | G10: =$D3 -> 0.0004138 | I10: =E10*$D3 -> 0
A11: 5 | E11: 0 | G11: =$D3 -> 0.0004138 | I11: =E11*$D3 -> 0
A12: Subtotal — 📱 Social Media & Digital Marketing | E12: =SUM(E7:E11) -> 0 | I12: =SUM(I7:I11) -> 0
A13: 📞 Communication & Internet
A14: 6 | B14: Internet bundle — office | C14: Monthly broadband / data bundle | D14: Monthly | E14: 0 | G14: =$D3 -> 0.0004138 | I14: =E14*$D3 -> 0
A15: 7 | B15: Phone airtime / data | C15: Staff communication allowance | D15: Monthly | E15: 0 | G15: =$D3 -> 0.0004138 | I15: =E15*$D3 -> 0
A16: 8 | B16: WhatsApp Business API | C16: Community messaging tool | D16: Monthly | E16: 0 | G16: =$D3 -> 0.0004138 | I16: =E16*$D3 -> 0
A17: 9 | B17: Email service (if paid) | C17: Newsletter / mailing list tool | D17: Monthly | E17: 0 | G17: =$D3 -> 0.0004138 | I17: =E17*$D3 -> 0
A18: 10 | E18: 0 | G18: =$D3 -> 0.0004138 | I18: =E18*$D3 -> 0
A19: Subtotal — 📞 Communication & Internet | E19: =SUM(E14:E18) -> 0 | I19: =SUM(I14:I18) -> 0
A20: 🖨️ Printing & Stationery
A21: 11 | B21: Flyers & promotional material | C21: Event promotion printing | D21: Per event | E21: 0 | G21: =$D3 -> 0.0004138 | I21: =E21*$D3 -> 0
A22: 12 | B22: Certificates printing | C22: Participant certificates | D22: Per event | E22: 0 | G22: =$D3 -> 0.0004138 | I22: =E22*$D3 -> 0
A23: 13 | B23: Office stationery | C23: Pens, notebooks, folders | D23: Monthly | E23: 0 | G23: =$D3 -> 0.0004138 | I23: =E23*$D3 -> 0
A24: 14 | B24: Banner / rollup printing | C24: Event display materials | D24: Per event | E24: 0 | G24: =$D3 -> 0.0004138 | I24: =E24*$D3 -> 0
A25: 15 | E25: 0 | G25: =$D3 -> 0.0004138 | I25: =E25*$D3 -> 0
A26: Subtotal — 🖨️ Printing & Stationery | E26: =SUM(E21:E25) -> 0 | I26: =SUM(I21:I25) -> 0
A27: 🏦 Bank & Financial Charges
A28: 16 | B28: Bank transfer charges | C28: Receiving / sending grant funds | D28: Per transaction | E28: 0 | G28: =$D3 -> 0.0004138 | I28: =E28*$D3 -> 0
A29: 17 | B29: Mobile money charges | C29: M-Pesa / Airtel Money fees | D29: Per transaction | E29: 0 | G29: =$D3 -> 0.0004138 | I29: =E29*$D3 -> 0
A30: 18 | B30: Currency conversion fees | C30: FX conversion costs | D30: Per transaction | E30: 0 | G30: =$D3 -> 0.0004138 | I30: =E30*$D3 -> 0
A31: 19 | E31: 0 | G31: =$D3 -> 0.0004138 | I31: =E31*$D3 -> 0
A32: Subtotal — 🏦 Bank & Financial Charges | E32: =SUM(E28:E31) -> 0 | I32: =SUM(I28:I31) -> 0
A33: 📦 Other Operational Costs
A34: 20 | B34: Zoom / video call subscriptions | C34: Online meetings tool | D34: Monthly | E34: 0 | G34: =$D3 -> 0.0004138 | I34: =E34*$D3 -> 0
A35: 21 | B35: Cloud storage (Google Drive etc.) | C35: File storage subscription | D35: Monthly | E35: 0 | G35: =$D3 -> 0.0004138 | I35: =E35*$D3 -> 0
A36: 22 | B36: Domain / hosting fees | C36: Website or tool hosting | D36: Annual | E36: 0 | G36: =$D3 -> 0.0004138 | I36: =E36*$D3 -> 0
A37: 23 | B37: Office supplies | C37: Miscellaneous office items | D37: Monthly | E37: 0 | G37: =$D3 -> 0.0004138 | I37: =E37*$D3 -> 0
A38: 24 | B38: Reporting & documentation | C38: Report writing, translation costs | D38: Per report | E38: 0 | G38: =$D3 -> 0.0004138 | I38: =E38*$D3 -> 0
A39: 25 | E39: 0 | G39: =$D3 -> 0.0004138 | I39: =E39*$D3 -> 0
A40: Subtotal — 📦 Other Operational Costs | E40: =SUM(E34:E39) -> 0 | I40: =SUM(I34:I39) -> 0
A41: GRAND TOTAL — ADMINISTRATIVE COSTS | E41: =SUM(E6:E40) -> 0 | I41: =SUM(I6:I40) -> 0
